LICENSE
README.md
pyproject.toml
setup.cfg
setup.py
daqhats/__init__.py
daqhats/hats.py
daqhats/mcc118.py
daqhats/mcc128.py
daqhats/mcc134.py
daqhats/mcc152.py
daqhats/mcc172.py
daqhats.egg-info/PKG-INFO
daqhats.egg-info/SOURCES.txt
daqhats.egg-info/dependency_links.txt
daqhats.egg-info/top_level.txt