Metadata-Version: 2.1
Name: daqhats
Version: 1.4.1.0
Summary: MCC DAQ HAT Python Library
Home-page: https://github.com/mccdaq/daqhats
Author: Measurement Computing Corp.
Author-email: info@mccdaq.com
License: MIT
Classifier: Programming Language :: Python :: 3
Requires-Python: >=2.7
License-File: LICENSE
